mvpd/MVPD_lin_reg.py
mvpd/MVPD_neural_net.py
mvpd/__init__.py
mvpd/avgrun_neural_net.py
mvpd/avgrun_regression.py
mvpd/data_loading.py
mvpd/dim_red.py
mvpd/model_exec.py
mvpd/params_check.py
mvpd/custom_func/NN_custom.py
mvpd/custom_func/__init__.py
mvpd/custom_func/dimred_custom.py
mvpd/dataloader/__init__.py
mvpd/dataloader/loader_neural_net.py
mvpd/dataloader/loader_regression.py
mvpd/dimension_reduction/__init__.py
mvpd/dimension_reduction/dimred_base.py
mvpd/evaluation/__init__.py
mvpd/evaluation/var_expl.py
mvpd/func_regression/__init__.py
mvpd/func_regression/lin_reg.py
mvpd/preprocessing/__init__.py
mvpd/preprocessing/dataset_processing.py
mvpd/viz/__init__.py
mvpd/viz/viz_map.py
PyMVPD-0.0.4.dist-info/LICENSE
PyMVPD-0.0.4.dist-info/METADATA
PyMVPD-0.0.4.dist-info/WHEEL
PyMVPD-0.0.4.dist-info/top_level.txt
PyMVPD-0.0.4.dist-info/RECORD
