Metadata-Version: 2.1
Name: PyMVPD
Version: 0.0.4
Summary: A python package for multivariate pattern dependence
Home-page: https://github.com/sccnlab/PyMVPD
Author: Mengting Fang
Author-email: mtfang0707@gmail.com
License: UNKNOWN
Keywords: fMRI,MVPD,machine learning,connectivity
Platform: UNKNOWN
Classifier: Programming Language :: Python :: 3.6
Classifier: Programming Language :: Python :: 3.7
Classifier: Programming Language :: Python :: 3.8
Classifier: License :: OSI Approved :: MIT License
Classifier: Operating System :: OS Independent
Requires-Dist: nibabel (>=3.2.1)
Requires-Dist: numpy (>=1.19.3)
Requires-Dist: scikit-learn (>=0.20.1)
Requires-Dist: scipy (>=1.1.0)
